{"name": "工作邮件", "description": "内部工作沟通邮件", "fields": [{"id": "recipient", "label": "收件人", "hint": "收件人姓名/职位", "required": true}, {"id": "subject", "label": "邮件主题", "hint": "简明扼要的标题", "required": true}, {"id": "background", "label": "背景说明", "hint": "为什么发这封邮件", "required": true}, {"id": "content", "label": "核心内容", "hint": "邮件的详细内容", "required": true}, {"id": "action", "label": "行动项", "hint": "需要对方做什么"}, {"id": "deadline", "label": "截止时间", "hint": "需要什么时候前回复/完成"}, {"id": "audience", "label": "收件层级", "type": "select", "options": ["直属上级", "跨部门同事", "下属", "全员"]}, {"id": "tone", "label": "语气", "type": "select", "options": ["正式规范", "简洁高效", "友好协作"]}, {"id": "word_count", "label": "篇幅", "type": "select", "options": ["简要", "标准"]}]}