{"name":"商务邮件","description":"专业得体的商务往来邮件","example":"主题：关于Q3合作方案确认\n\n尊敬的王总：\n\n感谢贵司在Q2合作中的大力支持。现就Q3合作方案调整事宜与您确认如下：\n\n一、合作范围调整\n根据上次会议讨论，Q3合作范围将新增电商直播渠道...\n\n二、商务条款\n费用结算仍维持原有模式，新增渠道按独立项目计费...\n\n三、下一步计划\n烦请在6月5日前确认方案，以便我方安排资源对接...\n\n期待您的回复。\n\n顺祝商祺\n李经理\nXX公司商务拓展部","fields":[{"id":"recipient","label":"收件人","hint":"收件人姓名、职位","required":true},{"id":"subject","label":"邮件主题","hint":"简明扼要的邮件标题","required":true},{"id":"purpose","label":"邮件目的","hint":"发这封邮件的原因，一句话","required":true},{"id":"content","label":"核心内容","hint":"邮件的详细内容，可分条列","required":true},{"id":"action","label":"期望回复","hint":"希望对方怎么做，什么时间前回复"},{"id":"tone","label":"语气风格","hint":"选择合适的邮件语气","type":"select","options":["正式商务","简洁高效","亲和友好","专业严谨"]},{"id":"word_count","label":"期望篇幅","hint":"AI 将据此控制输出长度","type":"select","options":["简洁 (约200字)","标准 (约500字)","详细 (约800字)","不限"]}]}