{"name":"述职报告","description":"汇报工作成果与计划的正式报告","example":"2025年Q2述职报告\n\n述职人：张三\n岗位：市场部总监\n述职周期：2025年4月-6月\n\n一、岗位职责\n负责公司全线产品的市场营销和品牌推广，管理10人团队，年度市场预算500万元。\n\n二、工作成果\n1. 达成季度营收目标120%，实现营收1200万元\n2. 成功上线3个新品，累计获得客户200+家\n3. 品牌知名度提升35%，月均官网流量突破50万\n4. 团队建设：引进2名高级经理，团队战斗力显著提升\n\n三、问题反思\n1. 渠道拓展速度低于预期，西南区域覆盖不足\n2. 新品上市周期偏长，从立项到上线平均耗时4个月\n3. 竞品低价策略对部分客户产生分流影响\n\n四、改进措施\n1. Q3重点开拓西南市场，计划新增2个省级代理\n2. 优化产品开发流程，目标将上市周期压缩到3个月\n3. 推出差异化增值服务，降低价格敏感度\n\n五、下季度目标\n营收目标：1500万元 | 新客户数：100家 | 品牌认知度：提升至60%","fields":[{"id":"name","label":"述职人","hint":"姓名和岗位","required":true},{"id":"period","label":"述职周期","hint":"如：2025年Q1","required":true},{"id":"duty","label":"岗位职责","hint":"你的主要职责","required":true},{"id":"achievements","label":"工作成果","hint":"取得的具体成绩，用数据说话","required":true},{"id":"problems","label":"问题反思","hint":"工作中的不足和原因分析"},{"id":"improvement","label":"改进措施","hint":"针对问题的改进方案"},{"id":"next_plan","label":"下期计划","hint":"下阶段的目标和计划","required":true},{"id":"tone","label":"语气风格","hint":"选择述职报告的语气","type":"select","options":["客观务实","积极进取","诚恳反思"]},{"id":"word_count","label":"期望篇幅","hint":"控制报告长度","type":"select","options":["简洁","标准","详细"]}]}